aind_alert_utils/__init__.py
aind_alert_utils/teams.py
aind_alert_utils-0.1.3.dist-info/LICENSE
aind_alert_utils-0.1.3.dist-info/METADATA
aind_alert_utils-0.1.3.dist-info/WHEEL
aind_alert_utils-0.1.3.dist-info/top_level.txt
aind_alert_utils-0.1.3.dist-info/RECORD
